books_recommendor_pkg/__init__.py
books_recommendor_pkg/fetch_best_books.py
books_recommender_pkg_Preeti_Rawat-0.0.3.dist-info/LICENSE
books_recommender_pkg_Preeti_Rawat-0.0.3.dist-info/METADATA
books_recommender_pkg_Preeti_Rawat-0.0.3.dist-info/WHEEL
books_recommender_pkg_Preeti_Rawat-0.0.3.dist-info/top_level.txt
books_recommender_pkg_Preeti_Rawat-0.0.3.dist-info/RECORD
